poser.py
poser-0.2.3.dist-info/LICENSE
poser-0.2.3.dist-info/WHEEL
poser-0.2.3.dist-info/METADATA
poser-0.2.3.dist-info/RECORD
