Metadata-Version: 2.1
Name: poser
Version: 0.2.3
Summary: dysfunctional programming in python
Home-page: https://github.com/deathbeds/poser
License: BSD-3-Clause
Keywords: 
Author: deathbeds
Author-email: tony.fast@gmail.com
Requires-Dist: toolz
